fn_graph_studio/__init__.py
fn_graph_studio/assets/favicon.ico
fn_graph_studio/cli.py
fn_graph_studio/highlight.css
fn_graph_studio/layout_helpers.py
fn_graph_studio/parameter_editor.py
fn_graph_studio/result_renderers.py
fn_graph_studio/styles.css
fn_graph_studio-0.10.5.dist-info/entry_points.txt
fn_graph_studio-0.10.5.dist-info/WHEEL
fn_graph_studio-0.10.5.dist-info/METADATA
fn_graph_studio-0.10.5.dist-info/RECORD
