Metadata-Version: 2.1
Name: fn-graph-studio
Version: 0.10.5
Summary: A web based explorer for fn_graph function composers
Home-page: https://github.com/BusinessOptics/fn_graph_studio
License: MIT
Author: James Saunders
Author-email: james@businessoptics.biz
Requires-Python: >=3.7,<4.0
Classifier: License :: OSI Approved :: MIT License
Classifier: Programming Language :: Python :: 3
Classifier: Programming Language :: Python :: 3.7
Classifier: Programming Language :: Python :: 3.8
Requires-Dist: dash (>=1.10,<2.0)
Requires-Dist: dash-ace-persistent (>=0.3.4,<0.4.0)
Requires-Dist: dash-cytoscape (>=0.1.1,<0.2.0)
Requires-Dist: dash-dangerously-set-inner-html (>=0.0.2,<0.0.3)
Requires-Dist: dash-treebeard (>=0.0.1,<0.0.2)
Requires-Dist: dash_core_components (>=1.0,<2.0)
Requires-Dist: dash_interactive_graphviz (>=0.2.0,<0.3.0)
Requires-Dist: dash_split_pane (>=1.0,<2.0)
Requires-Dist: fn_graph[examples]
Requires-Dist: matplotlib (>=3.2.1,<4.0.0)
Requires-Dist: networkx (>=2.4,<3.0)
Requires-Dist: pandas (>=0.25.3)
Requires-Dist: plotly (>=4.0,<5.0)
Requires-Dist: pygments (>=2.6.1,<3.0.0)
Requires-Dist: seaborn (>=0.10.0,<0.11.0)
Requires-Dist: sh (>=1.0,<2.0)
Requires-Dist: statsmodels (>=0.11.1,<0.12.0)
Project-URL: Documentation, https://fn-graph.readthedocs.io/
Project-URL: Repository, https://github.com/BusinessOptics/fn_graph_studio
